image_transform/__init__.py
image_transform/image_transform.py
transformIMG-0.0.1.1.dist-info/LICENSE.txt
transformIMG-0.0.1.1.dist-info/METADATA
transformIMG-0.0.1.1.dist-info/WHEEL
transformIMG-0.0.1.1.dist-info/top_level.txt
transformIMG-0.0.1.1.dist-info/RECORD
